{
 "threshold": 0.489,
 "overall": {
  "n": 500,
  "n_malignant": 250,
  "accuracy": 0.806,
  "recall": 0.8,
  "precision": 0.8097,
  "auc": 0.8991
 },
 "by_sex": [
  {
   "sex": "female",
   "n": 218,
   "accuracy": 0.8028,
   "recall": 0.7158
  },
  {
   "sex": "male",
   "n": 282,
   "accuracy": 0.8085,
   "recall": 0.8516
  }
 ],
 "by_location": [
  {
   "loc": "back",
   "n": 123,
   "n_malignant": 67,
   "malignant_rate": 0.545,
   "accuracy": 0.7886,
   "recall": 0.806,
   "reliable": true
  },
  {
   "loc": "lower extremity",
   "n": 103,
   "n_malignant": 41,
   "malignant_rate": 0.398,
   "accuracy": 0.8641,
   "recall": 0.878,
   "reliable": true
  },
  {
   "loc": "upper extremity",
   "n": 55,
   "n_malignant": 35,
   "malignant_rate": 0.636,
   "accuracy": 0.7455,
   "recall": 0.7429,
   "reliable": true
  },
  {
   "loc": "trunk",
   "n": 53,
   "n_malignant": 12,
   "malignant_rate": 0.226,
   "accuracy": 0.8491,
   "recall": 0.6667,
   "reliable": true
  },
  {
   "loc": "face",
   "n": 52,
   "n_malignant": 38,
   "malignant_rate": 0.731,
   "accuracy": 0.8462,
   "recall": 0.9211,
   "reliable": true
  },
  {
   "loc": "abdomen",
   "n": 38,
   "n_malignant": 10,
   "malignant_rate": 0.263,
   "accuracy": 0.6842,
   "recall": 0.2,
   "reliable": true
  },
  {
   "loc": "chest",
   "n": 23,
   "n_malignant": 18,
   "malignant_rate": 0.783,
   "accuracy": 0.7826,
   "recall": 0.8333,
   "reliable": true
  },
  {
   "loc": "foot",
   "n": 18,
   "n_malignant": 7,
   "malignant_rate": 0.389,
   "accuracy": 0.9444,
   "recall": 0.8571,
   "reliable": false
  },
  {
   "loc": "neck",
   "n": 12,
   "n_malignant": 10,
   "malignant_rate": 0.833,
   "accuracy": 0.9167,
   "recall": 0.9,
   "reliable": false
  },
  {
   "loc": "unknown",
   "n": 10,
   "n_malignant": 5,
   "malignant_rate": 0.5,
   "accuracy": 0.7,
   "recall": 0.6,
   "reliable": false
  },
  {
   "loc": "scalp",
   "n": 9,
   "n_malignant": 7,
   "malignant_rate": 0.778,
   "accuracy": 0.7778,
   "recall": 0.8571,
   "reliable": false
  },
  {
   "loc": "ear",
   "n": 2,
   "n_malignant": 0,
   "malignant_rate": 0.0,
   "accuracy": 0.0,
   "recall": null,
   "reliable": false
  },
  {
   "loc": "hand",
   "n": 1,
   "n_malignant": 0,
   "malignant_rate": 0.0,
   "accuracy": 1.0,
   "recall": null,
   "reliable": false
  },
  {
   "loc": "genital",
   "n": 1,
   "n_malignant": 0,
   "malignant_rate": 0.0,
   "accuracy": 0.0,
   "recall": null,
   "reliable": false
  }
 ],
 "by_age": [
  {
   "bucket": "0-30",
   "n": 22,
   "n_malignant": 4,
   "malignant_rate": 0.182,
   "accuracy": 0.7727,
   "recall": 0.5
  },
  {
   "bucket": "30-45",
   "n": 73,
   "n_malignant": 18,
   "malignant_rate": 0.247,
   "accuracy": 0.7808,
   "recall": 0.5556
  },
  {
   "bucket": "45-60",
   "n": 171,
   "n_malignant": 60,
   "malignant_rate": 0.351,
   "accuracy": 0.8129,
   "recall": 0.7
  },
  {
   "bucket": "60-75",
   "n": 136,
   "n_malignant": 95,
   "malignant_rate": 0.699,
   "accuracy": 0.8235,
   "recall": 0.8632
  },
  {
   "bucket": "75+",
   "n": 98,
   "n_malignant": 73,
   "malignant_rate": 0.745,
   "accuracy": 0.7959,
   "recall": 0.8767
  }
 ],
 "calibration": {
  "mean_confidence_correct": 0.415,
  "mean_confidence_wrong": 0.256,
  "n_wrong": 97,
  "confidently_wrong": 42,
  "confidently_wrong_pct": 43.3
 },
 "errors": {
  "false_negatives": 50,
  "false_positives": 47,
  "fn_mean_age": 55.0,
  "malignant_mean_age": 63.3,
  "benign_mean_age": 49.5
 },
 "examples": {
  "confident_correct_malignant": {
   "id": 96,
   "img": "img/96_orig.jpg",
   "cam": "img/96_cam.jpg",
   "prob": 1.0,
   "pred": "malignant",
   "true": "malignant",
   "correct": true,
   "age": 65.0,
   "sex": "male",
   "loc": "face",
   "x": 0.0043,
   "y": 0.7235
  },
  "confident_correct_benign": {
   "id": 3,
   "img": "img/3_orig.jpg",
   "cam": "img/3_cam.jpg",
   "prob": 0.0,
   "pred": "benign",
   "true": "benign",
   "correct": true,
   "age": 60.0,
   "sex": "male",
   "loc": "back",
   "x": 0.6246,
   "y": 0.2096
  },
  "confidently_missed_malignant": {
   "id": 330,
   "img": "img/330_orig.jpg",
   "cam": "img/330_cam.jpg",
   "prob": 0.0,
   "pred": "benign",
   "true": "malignant",
   "correct": false,
   "age": 50.0,
   "sex": "female",
   "loc": "back",
   "x": 0.779,
   "y": 0.27
  },
  "confidently_false_alarm": {
   "id": 401,
   "img": "img/401_orig.jpg",
   "cam": "img/401_cam.jpg",
   "prob": 0.998,
   "pred": "malignant",
   "true": "benign",
   "correct": false,
   "age": 65.0,
   "sex": "male",
   "loc": "back",
   "x": 0.0326,
   "y": 0.508
  }
 }
}